econagents/__init__.py
econagents/_c_extension.pyi
econagents/cli.py
econagents/config_parser/__init__.py
econagents/config_parser/base.py
econagents/config_parser/basic.py
econagents/core/__init__.py
econagents/core/agent_role.py
econagents/core/events.py
econagents/core/game_runner.py
econagents/core/logging_mixin.py
econagents/core/manager/__init__.py
econagents/core/manager/base.py
econagents/core/manager/phase.py
econagents/core/state/__init__.py
econagents/core/state/fields.py
econagents/core/state/game.py
econagents/core/transport.py
econagents/llm/__init__.py
econagents/llm/base.py
econagents/llm/observability.py
econagents/llm/ollama.py
econagents/llm/openai.py
econagents/py.typed
econagents-0.0.10.dist-info/LICENSE
econagents-0.0.10.dist-info/METADATA
econagents-0.0.10.dist-info/WHEEL
econagents-0.0.10.dist-info/entry_points.txt
econagents-0.0.10.dist-info/RECORD
