Metadata-Version: 2.3
Name: econagents
Version: 0.0.10
Summary: 
License: MIT
Author: Dylan Castillo
Author-email: dylan@iwanalabs.com
Requires-Python: >=3.10,<4
Classifier: License :: OSI Approved :: MIT License
Classifier: Programming Language :: Python :: 3
Classifier: Programming Language :: Python :: 3.10
Classifier: Programming Language :: Python :: 3.11
Classifier: Programming Language :: Python :: 3.12
Classifier: Programming Language :: Python :: 3.13
Provides-Extra: all
Provides-Extra: langfuse
Provides-Extra: langsmith
Provides-Extra: ollama
Provides-Extra: openai
Provides-Extra: standard
Requires-Dist: langfuse (>=3.0.3)
Requires-Dist: langfuse ; extra == "all"
Requires-Dist: langfuse ; extra == "langfuse"
Requires-Dist: langsmith (>=0.4.1)
Requires-Dist: langsmith ; extra == "all"
Requires-Dist: langsmith ; extra == "langsmith"
Requires-Dist: langsmith ; extra == "standard"
Requires-Dist: ollama (>=0.5.1)
Requires-Dist: ollama ; extra == "all"
Requires-Dist: ollama ; extra == "ollama"
Requires-Dist: openai (>=1.89.0)
Requires-Dist: openai ; extra == "all"
Requires-Dist: openai ; extra == "openai"
Requires-Dist: openai ; extra == "standard"
Requires-Dist: pydantic (>=2.11.5)
Requires-Dist: requests (>=2.32.4)
Requires-Dist: websockets (>=15.0)
